{"article": [{"url": "https://www.marketwatch.com/story/coronavirus-update-us-death-toll-nears-200000-with-24-states-showing-a-rise-in-case-tally-trends-2020-06-22", "published": 1592807540.0, "headline": "Coronavirus update: U.S. death toll nears 120,000, with 24 states showing a rise in case tally trends", "body": "The global tally for cases of the coronavirus that causes COVID-19 rose to just shy of 9 million on Monday, according to data aggregated by Johns Hopkins University. The number of deaths grew to 468,567, while the number of people who have recovered reached 4.4 million. The U.S. continues to lead the world, with the case tally of 2.28 million and death toll of 119,977 more than double the next highest totals of 1.08 million cases and 50,591 deaths in Brazil. In the U.S., 622,133 have recovered, while 588,118 have recovered in Brazil. Within the U.S., there are 24 states that showed an increasing trend in cases this past week, with California, Texas and Florida leading the way, each with more than 4,000 new cases on Sunday alone. Internationally, Russia was third in cases with 591,465, followed by India with 425,282 and the U.K. with 305,803, while after Brazil, death tolls were 42,717 for the U.K., 34,634 for Italy and 29,643 for France."}]}